README.md
decanter_ai_sdk/__init__.py
decanter_ai_sdk/client.py
decanter_ai_sdk/enums/algorithms.py
decanter_ai_sdk/enums/data_types.py
decanter_ai_sdk/enums/evaluators.py
decanter_ai_sdk/enums/missing_value_handling.py
decanter_ai_sdk/enums/status.py
decanter_ai_sdk/enums/time_units.py
decanter_ai_sdk/experiment.py
decanter_ai_sdk/model.py
decanter_ai_sdk/non_blocking_client.py
decanter_ai_sdk/prediction.py
decanter_ai_sdk/web_api/api.py
decanter_ai_sdk/web_api/data/iid_exp.json
decanter_ai_sdk/web_api/data/iid_predict.json
decanter_ai_sdk/web_api/data/iid_test_table.json
decanter_ai_sdk/web_api/data/iid_train_table.json
decanter_ai_sdk/web_api/data/model_list.json
decanter_ai_sdk/web_api/data/table_info.json
decanter_ai_sdk/web_api/data/table_list.json
decanter_ai_sdk/web_api/data/ts_exp.json
decanter_ai_sdk/web_api/data/ts_predict.json
decanter_ai_sdk/web_api/data/ts_test_table.json
decanter_ai_sdk/web_api/data/ts_train_table.json
decanter_ai_sdk/web_api/decanter_api.py
decanter_ai_sdk/web_api/iid_testing_api.py
decanter_ai_sdk/web_api/ts_testing_api.py
decanter_ai_sdk-0.1.21.dist-info/LICENSE
decanter_ai_sdk-0.1.21.dist-info/METADATA
decanter_ai_sdk-0.1.21.dist-info/WHEEL
decanter_ai_sdk-0.1.21.dist-info/RECORD
