Metadata-Version: 2.1
Name: decanter-ai-sdk
Version: 0.1.21
Summary: Decanter AI is a powerful AutoML tool which enables everyone to build ML models and make predictions without data science background. With Decanter AI SDK, you can integrate Decanter AI into your application more easily with Python.
Home-page: https://github.com/MoBagel/decanter-ai-sdk
Author: senchao
Author-email: senchao@mobagel.com
Requires-Python: >=3.8,<4.0
Classifier: Programming Language :: Python :: 3
Classifier: Programming Language :: Python :: 3.8
Classifier: Programming Language :: Python :: 3.9
Classifier: Programming Language :: Python :: 3.10
Classifier: Programming Language :: Python :: 3.11
Requires-Dist: pandas (>=1.4.3,<2.0.0)
Requires-Dist: pydantic (>=1.9.2,<2.0.0)
Requires-Dist: requests-toolbelt (>=0.9.1,<0.10.0)
Requires-Dist: tqdm (>=4.64.0,<5.0.0)
Requires-Dist: urllib3 (==1.26.15)
